tmxconverter/__init__.py
tmxconverter/convert.py
tmxconverter/save2files.py
tmxconverter/save2hdb.py
tmxconverter-0.0.6.dist-info/LICENSE
tmxconverter-0.0.6.dist-info/METADATA
tmxconverter-0.0.6.dist-info/WHEEL
tmxconverter-0.0.6.dist-info/entry_points.txt
tmxconverter-0.0.6.dist-info/top_level.txt
tmxconverter-0.0.6.dist-info/RECORD
