Metadata-Version: 2.1
Name: tmxconverter
Version: 0.0.6
Summary: Converts TMX files to CSV-files and/or stores to HANA table
Home-page: https://github.com/thhapke/tmxconverter
Author: Thorsten Hapke
Author-email: thorsten.hapke@sap.com
License: UNKNOWN
Keywords: tmx
Platform: UNKNOWN
Classifier: Programming Language :: Python :: 3.6
Classifier: Programming Language :: Python :: 3.7
Classifier: Programming Language :: Python :: 3.8
Classifier: License :: OSI Approved :: MIT License
Classifier: Operating System :: OS Independent
Requires-Dist: pandas
Requires-Dist: pyyaml
Requires-Dist: hdbcli
